{
  "id": "gid://shopify/Order/1001",
  "processedAt": "2024-01-15T12:00:00-06:00",
  "cancelledAt": null,
  "test": false,
  "currentSubtotalPriceSet": {
    "shopMoney": { "amount": "1000.00", "currencyCode": "MXN" }
  },
  "currentShippingPriceSet": {
    "shopMoney": { "amount": "100.00", "currencyCode": "MXN" }
  },
  "currentTotalTaxSet": {
    "shopMoney": { "amount": "160.00", "currencyCode": "MXN" }
  },
  "currentTotalDiscountsSet": {
    "shopMoney": { "amount": "0.00", "currencyCode": "MXN" }
  },
  "refunds": {
    "nodes": []
  }
}
